laziest/__init__.py
laziest/analyzer.py
laziest/argsgen.py
laziest/asserter.py
laziest/ast_meta.py
laziest/codegen.py
laziest/conf/__init__.py
laziest/conf/cli.py
laziest/conf/cli.yaml
laziest/conf/config.py
laziest/conf/default_conf.cfg
laziest/core.py
laziest/diff.py
laziest/params.py
laziest/strings.py
laziest/utils.py
laziest/walker.py
laziest-0.0.dev6.dist-info/entry_points.txt
laziest-0.0.dev6.dist-info/LICENSE
laziest-0.0.dev6.dist-info/WHEEL
laziest-0.0.dev6.dist-info/METADATA
laziest-0.0.dev6.dist-info/RECORD
