Metadata-Version: 2.1
Name: laziest
Version: 0.0.dev6
Summary: 
Home-page: https://github.com/xnuinside/laziest
License: MIT
Author: xnuinside
Author-email: xnuinside@gmail.com
Requires-Python: >=3.7,<4.0
Classifier: License :: OSI Approved :: MIT License
Classifier: Programming Language :: Python :: 3
Classifier: Programming Language :: Python :: 3.7
Requires-Dist: black (>=18.3-alpha.0,<19.0)
Requires-Dist: clifier (>=0.0.3,<0.0.4)
Requires-Dist: codegraph (>=0.0.4,<0.0.5)
Requires-Dist: jedi (>=0.16.0,<0.17.0)
Project-URL: Repository, https://github.com/xnuinside/laziest
